activations/__init__.py
activations/apl.py
activations/arelu.py
activations/gelu.py
activations/maxout.py
activations/mixture.py
activations/slaf.py
activations/swish.py
activations/pau/__init__.py
activations/pau/torchsummary.py
activations/pau/utils.py
models/__init__.py
models/conv.py
models/linear.py
models/mini_imagenet_cnn.py
models/models.py
visualize/__init__.py
visualize/continuous_error_bars.py
visualize/visualize.py
activations-0.1.0.dist-info/LICENSE
activations-0.1.0.dist-info/METADATA
activations-0.1.0.dist-info/WHEEL
activations-0.1.0.dist-info/top_level.txt
activations-0.1.0.dist-info/RECORD
