Metadata-Version: 2.1
Name: activations
Version: 0.1.0
Summary: activations: a package contains different kinds of activation functions
Home-page: https://github.com/densechen/AReLU
Author: densechen
Author-email: densechen@foxmail.com
License: MIT
Download-URL: https://github.com/densechen/AReLU/archive/master.zip
Platform: UNKNOWN
Classifier: Programming Language :: Python :: 3 :: Only
Classifier: Operating System :: OS Independent
Requires-Python: >=3.6
Requires-Dist: torch
